LICENSE
README.md
pyproject.toml
setup.cfg
setup.py
src/cyberfusion/ClusterCli/__init__.py
src/cyberfusion/CoreCli/__init__.py
src/cyberfusion/CoreCli/_utilities.py
src/cyberfusion/CoreCli/api_users.py
src/cyberfusion/CoreCli/basic_authentication_realms.py
src/cyberfusion/CoreCli/borg.py
src/cyberfusion/CoreCli/certificate_managers.py
src/cyberfusion/CoreCli/certificates.py
src/cyberfusion/CoreCli/clusters.py
src/cyberfusion/CoreCli/cmses.py
src/cyberfusion/CoreCli/crons.py
src/cyberfusion/CoreCli/custom_config_snippets.py
src/cyberfusion/CoreCli/custom_configs.py
src/cyberfusion/CoreCli/customers.py
src/cyberfusion/CoreCli/daemons.py
src/cyberfusion/CoreCli/databases.py
src/cyberfusion/CoreCli/domain_routers.py
src/cyberfusion/CoreCli/firewall_groups.py
src/cyberfusion/CoreCli/firewall_rules.py
src/cyberfusion/CoreCli/fpm_pools.py
src/cyberfusion/CoreCli/ftp_users.py
src/cyberfusion/CoreCli/haproxy_listens.py
src/cyberfusion/CoreCli/hosts_entries.py
src/cyberfusion/CoreCli/htpasswd.py
src/cyberfusion/CoreCli/logs.py
src/cyberfusion/CoreCli/mail.py
src/cyberfusion/CoreCli/main.py
src/cyberfusion/CoreCli/malwares.py
src/cyberfusion/CoreCli/mariadb_encryption_keys.py
src/cyberfusion/CoreCli/nodes.py
src/cyberfusion/CoreCli/passenger_apps.py
src/cyberfusion/CoreCli/redis_instances.py
src/cyberfusion/CoreCli/security_txt_policies.py
src/cyberfusion/CoreCli/sites.py
src/cyberfusion/CoreCli/ssh_keys.py
src/cyberfusion/CoreCli/task_collections.py
src/cyberfusion/CoreCli/unix_users.py
src/cyberfusion/CoreCli/url_redirects.py
src/cyberfusion/CoreCli/virtual_hosts.py
src/python3_cyberfusion_cluster_cli.egg-info/PKG-INFO
src/python3_cyberfusion_cluster_cli.egg-info/SOURCES.txt
src/python3_cyberfusion_cluster_cli.egg-info/dependency_links.txt
src/python3_cyberfusion_cluster_cli.egg-info/entry_points.txt
src/python3_cyberfusion_cluster_cli.egg-info/requires.txt
src/python3_cyberfusion_cluster_cli.egg-info/top_level.txt