Metadata-Version: 2.1
Name: python3-cyberfusion-cluster-cli
Version: 1.11.5.1.2
Summary: CLI for Core API.
Home-page: https://vcs.cyberfusion.nl/core/python3-cyberfusion-core-cli
Author: William Edwards
Author-email: wedwards@cyberfusion.nl
License: MIT
Keywords: cyberfusion,core,cli
Platform: linux
Classifier: Programming Language :: Python :: 3
Classifier: License :: OSI Approved :: MIT License
Classifier: Operating System :: OS Independent
Requires-Python: >=3.9
Provides-Extra: borg
License-File: LICENSE
